plutocontrol/Pluto.py
plutocontrol/__init__.py
plutocontrol-0.2.0.dist-info/LICENSE
plutocontrol-0.2.0.dist-info/METADATA
plutocontrol-0.2.0.dist-info/WHEEL
plutocontrol-0.2.0.dist-info/top_level.txt
plutocontrol-0.2.0.dist-info/RECORD
