Metadata-Version: 2.1
Name: plutocontrol
Version: 0.2.0
Summary: A library for controlling Pluto drones
Home-page: https://github.com/DronaAviation/plutocontrol.git
Author: Saail Chavan
Author-email: saailchavan02@gmail.com
License: UNKNOWN
Platform: UNKNOWN
Classifier: Programming Language :: Python :: 3
Classifier: License :: OSI Approved :: MIT License
Classifier: Operating System :: OS Independent
